agent_flows_builder/__init__.py
agent_flows_builder/_version.py
agent_flows_builder/settings.py
agent_flows_builder/agents/__init__.py
agent_flows_builder/agents/deployment.py
agent_flows_builder/agents/flow_builder_master.py
agent_flows_builder/agents/sub_agents/__init__.py
agent_flows_builder/agents/sub_agents/configuration_expert.py
agent_flows_builder/agents/sub_agents/configuration_reference_specialist.py
agent_flows_builder/agents/sub_agents/flow_architect.py
agent_flows_builder/agents/sub_agents/flow_validator.py
agent_flows_builder/checkpointers/__init__.py
agent_flows_builder/checkpointers/sqlite.py
agent_flows_builder/config/__init__.py
agent_flows_builder/config/settings.py
agent_flows_builder/middleware/__init__.py
agent_flows_builder/middleware/context_injection.py
agent_flows_builder/middleware/tool_allowlist.py
agent_flows_builder/prompts/__init__.py
agent_flows_builder/prompts/config_expert.py
agent_flows_builder/prompts/config_reference.py
agent_flows_builder/prompts/flow_architect.py
agent_flows_builder/prompts/flow_validator.py
agent_flows_builder/prompts/master.py
agent_flows_builder/prompts/tools.py
agent_flows_builder/resources/__init__.py
agent_flows_builder/resources/loaders.py
agent_flows_builder/resources/docs/examples/api-data-analysis.json
agent_flows_builder/resources/docs/examples/basic-api-call.json
agent_flows_builder/resources/docs/examples/content-generation.json
agent_flows_builder/resources/docs/examples/user-role-routing.json
agent_flows_builder/resources/docs/executors/apiCall.md
agent_flows_builder/resources/docs/executors/codeInterpreter.md
agent_flows_builder/resources/docs/executors/conditional.md
agent_flows_builder/resources/docs/executors/finish.md
agent_flows_builder/resources/docs/executors/flow_variables.md
agent_flows_builder/resources/docs/executors/llmInstruction.md
agent_flows_builder/resources/docs/executors/loop.md
agent_flows_builder/resources/docs/executors/mcpServerAction.md
realtimex_agent_flows_builder-0.6.1.dist-info/METADATA
realtimex_agent_flows_builder-0.6.1.dist-info/WHEEL
realtimex_agent_flows_builder-0.6.1.dist-info/RECORD
