Metadata-Version: 2.4
Name: realtimex-agent-flows-builder
Version: 0.6.1
Summary: AI Agent that builds workflow automations via natural language
Project-URL: Repository, https://rtgit.rta.vn/rtlab/rtwebteam/realtimex-agent-flows-builder
Project-URL: Issues, https://rtgit.rta.vn/rtlab/rtwebteam/realtimex-agent-flows-builder/issues
Author-email: RealTime <info@realtimex.ai>
License: MIT
Keywords: agents,ai,automation,langgraph,workflow
Requires-Python: >=3.11
Requires-Dist: arize-phoenix-otel>=0.13.1
Requires-Dist: jsonpath-ng>=1.7.0
Requires-Dist: langchain-openai>=0.3.32
Requires-Dist: langgraph-checkpoint-sqlite>=2.0.11
Requires-Dist: openinference-instrumentation-langchain>=0.1.58
Requires-Dist: python-dotenv>=1.1.1
Requires-Dist: realtimex-agent-flows
Requires-Dist: realtimex-deepagents
